hktkzyx_toolbox/__init__.py
hktkzyx_toolbox/electronics.py
hktkzyx_toolbox/finance/__init__.py
hktkzyx_toolbox/finance/social_pension.py
hktkzyx_toolbox/misc.py
hktkzyx_toolbox/scripts/__init__.py
hktkzyx_toolbox/scripts/electronics.py
hktkzyx_toolbox/scripts/finance.py
hktkzyx_toolbox-1.0.1.dist-info/entry_points.txt
hktkzyx_toolbox-1.0.1.dist-info/LICENSE
hktkzyx_toolbox-1.0.1.dist-info/WHEEL
hktkzyx_toolbox-1.0.1.dist-info/METADATA
hktkzyx_toolbox-1.0.1.dist-info/RECORD
