Metadata-Version: 2.1
Name: hktkzyx-toolbox
Version: 1.0.1
Summary: Toolbox of hktkzyx.
Home-page: https://hktkzyx.github.io/hktkzyx-toolbox/
License: MulanPSL-2.0
Keywords: toolbox,click
Author: Brooks YUAN
Author-email: hktkzyx@yeah.net
Requires-Python: >=3.8,<3.10
Classifier: License :: OSI Approved
Classifier: License :: Other/Proprietary License
Classifier: Natural Language :: Chinese (Simplified)
Classifier: Natural Language :: English
Classifier: Programming Language :: Python
Classifier: Programming Language :: Python :: 3
Classifier: Programming Language :: Python :: 3.8
Classifier: Programming Language :: Python :: 3.9
Provides-Extra: docs
Provides-Extra: test
Requires-Dist: click (>=8.0.4,<9.0.0)
Requires-Dist: mike (>=1.1.2,<2.0.0); extra == "docs"
Requires-Dist: mkdocs (>=1.3.0,<2.0.0); extra == "docs"
Requires-Dist: mkdocs-material (>=8.2.8,<9.0.0); extra == "docs"
Requires-Dist: mkdocstrings-python-legacy (>=0.2.2,<0.3.0); extra == "docs"
Requires-Dist: numpy (>=1.22.3,<2.0.0)
Requires-Dist: pytest (>=7.1.1,<8.0.0); extra == "test"
Requires-Dist: pytest-cov (>=3.0.0,<4.0.0); extra == "test"
Requires-Dist: pytkdocs[numpy-style] (>=0.16.1,<0.17.0); extra == "docs"
Requires-Dist: scipy (>=1.7.1,<2.0.0)
Project-URL: Documentation, https://hktkzyx.github.io/hktkzyx-toolbox/
Project-URL: Repository, https://github.com/hktkzyx/hktkzyx-toolbox
